{
    "menu": [
        {
            "denominacion": "nivel 1",
            "url": "http://www.google.es",
            "hijos": [
                {
                    "denominacion": "nivel 1.1",
                    "url": "http://www.google.es",
                    "target": "_blank"
          },
                {
                    "denominacion": "nivel 1.2",
                    "url": "http://www.google.es",
                    "hijos": [
                        {
                            "denominacion": "nivel 1.2.1",
                            "url": "http://www.google.es",
                            "target": "_blank"
              },
                        {
                            "denominacion": "nivel 1.2.2",
                            "url": "http://www.google.es",
                            "target": "_blank"
              }
            ]
          }
          ]
      },
        {
            "denominacion": "nivel 2",
            "url": "http://www.google.es",
            "hijos": [
                {
                    "denominacion": "nivel 2.1",
                    "url": "http://www.google.es",
                    "target": "_blank"
          },
                {
                    "denominacion": "nivel 2.2",
                    "url": "http://www.google.es"
          }

        ]
      },
        {
            "denominacion": "nivel 3",
            "url": "http://www.google.es"
      },
        {
            "denominacion": "nivel 3",
            "url": "http://www.google.es",
            "hijos": [
                {
                    "denominacion": "nivel 3.1",
                    "url": "http://www.google.es",
                    "target": "_blank"
          },
                {
                    "denominacion": "nivel 3.2",
                    "url": "http://www.google.es",
                    "hijos": [
                        {
                            "denominacion": "nivel 3.2.1",
                            "url": "http://www.google.es",
                            "target": "_blank"
              },
                        {
                            "denominacion": "nivel 3.2.2",
                            "url": "http://www.google.es",
                            "target": "_blank"
              }
            ]
          }
          ]
      }
    ]
}
